tarraz/__init__.py
tarraz/colors/__init__.py
tarraz/colors/dmc.py
tarraz/constants.py
tarraz/logger.py
tarraz/main.py
tarraz/models.py
tarraz/processor.py
tarraz/providers/__init__.py
tarraz/providers/dmc.py
tarraz/providers/provider.py
tarraz/stitcher/__init__.py
tarraz/stitcher/display.py
tarraz/stitcher/stitcher.py
tarraz/stitcher/svg.py
tarraz/utils.py
tarraz-1.2.1.dist-info/LICENSE
tarraz-1.2.1.dist-info/METADATA
tarraz-1.2.1.dist-info/WHEEL
tarraz-1.2.1.dist-info/entry_points.txt
tarraz-1.2.1.dist-info/RECORD
