Metadata-Version: 2.1
Name: tarraz
Version: 1.2.1
Summary: A cross-stitch image generator. Generates a cross stitch pattern given by a user and generates a DMC colored pattern.
Home-page: https://www.nitfe.com/
License: GNU Affero General Public License v3
Keywords: cross-stitch,pattern,stitch,DMC
Author: Ahmed Jazzar
Author-email: ahmed@nitfe.com
Requires-Python: >=3.8
Classifier: Development Status :: 5 - Production/Stable
Classifier: Intended Audience :: Developers
Classifier: License :: OSI Approved :: GNU Affero General Public License v3
Classifier: License :: Other/Proprietary License
Classifier: Operating System :: OS Independent
Classifier: Programming Language :: Python :: 3
Classifier: Programming Language :: Python :: 3.8
Classifier: Programming Language :: Python :: 3.9
Classifier: Programming Language :: Python :: 3.10
Classifier: Programming Language :: Python :: 3.11
Classifier: Programming Language :: Python :: 3.12
Classifier: Topic :: Software Development
Requires-Dist: pillow (>=9.5.0)
Project-URL: Changelog, https://github.com/nitfe/tarraz/releases
Project-URL: Documentation, https://github.com/nitfe/tarraz/blob/main/README.md
Project-URL: Issues, https://github.com/nitfe/tarraz/issues
Project-URL: Repository, https://github.com/nitfe/tarraz.git
